mizdb_watchlist/__init__.py
mizdb_watchlist/actions.py
mizdb_watchlist/admin.py
mizdb_watchlist/apps.py
mizdb_watchlist/locale/de/LC_MESSAGES/django.mo
mizdb_watchlist/locale/de/LC_MESSAGES/django.po
mizdb_watchlist/manager.py
mizdb_watchlist/migrations/0001_initial.py
mizdb_watchlist/migrations/__init__.py
mizdb_watchlist/models.py
mizdb_watchlist/static/mizdb_watchlist/css/watchlist.css
mizdb_watchlist/static/mizdb_watchlist/css/watchlist_toggle.css
mizdb_watchlist/static/mizdb_watchlist/js/watchlist.js
mizdb_watchlist/static/mizdb_watchlist/js/watchlist_init.js
mizdb_watchlist/templates/admin/watchlist.html
mizdb_watchlist/templates/mizdb_watchlist/toggle_button.html
mizdb_watchlist/templates/mizdb_watchlist/watchlist.html
mizdb_watchlist/templates/mizdb_watchlist/watchlist_icon.svg
mizdb_watchlist/templates/mizdb_watchlist/watchlist_link.html
mizdb_watchlist/templatetags/__init__.py
mizdb_watchlist/templatetags/mizdb_watchlist.py
mizdb_watchlist/urls.py
mizdb_watchlist/views.py
mizdb_watchlist-1.1.1.dist-info/LICENSE
mizdb_watchlist-1.1.1.dist-info/METADATA
mizdb_watchlist-1.1.1.dist-info/WHEEL
mizdb_watchlist-1.1.1.dist-info/RECORD
