Metadata-Version: 2.1
Name: mizdb-watchlist
Version: 1.1.1
Summary: A watchlist for Django model objects.
Home-page: https://github.com/Actionb/mizdb-watchlist
License: MIT
Author: Philip Becker
Author-email: yummytea1@gmail.com
Requires-Python: >=3.9,<4.0
Classifier: Framework :: Django
Classifier: License :: OSI Approved :: MIT License
Classifier: Programming Language :: Python :: 3
Classifier: Programming Language :: Python :: 3.9
Classifier: Programming Language :: Python :: 3.10
Classifier: Programming Language :: Python :: 3.11
Classifier: Programming Language :: Python :: 3.12
Requires-Dist: django (>=4.2)
Project-URL: Repository, https://github.com/Actionb/mizdb-watchlist
